selee/__init__.py
selee/selee_module.py
tests/__init__.py
tests/unit_test.py
selee-0.2.dist-info/LICENSE
selee-0.2.dist-info/METADATA
selee-0.2.dist-info/WHEEL
selee-0.2.dist-info/top_level.txt
selee-0.2.dist-info/RECORD
