Metadata-Version: 2.1
Name: selee
Version: 0.2
Summary: package development exercise
Home-page: https://github.com/sophialee0628/selee
Author: Seung Eun (Sophia) Lee
Author-email: leeseungeun0628@gmail.com
License: UNKNOWN
Platform: UNKNOWN
Classifier: Programming Language :: Python :: 3
Classifier: Operating System :: OS Independent
Requires-Python: >=3.6
